lucylove/__init__.py
lucylove-0.0.2.dist-info/LICENSE
lucylove-0.0.2.dist-info/METADATA
lucylove-0.0.2.dist-info/WHEEL
lucylove-0.0.2.dist-info/top_level.txt
lucylove-0.0.2.dist-info/RECORD
