Metadata-Version: 2.1
Name: lucylove
Version: 0.0.2
Summary: Multifunctional package
Home-page: https://github.com/pypa/sampleproject
Author: Lucy
Author-email: adamballin1048@proton.me
Project-URL: Bug Tracker, https://github.com/pypa/sampleproject/issues
Classifier: Programming Language :: Python :: 3
Classifier: License :: OSI Approved :: MIT License
Classifier: Operating System :: OS Independent
Requires-Python: >=3.6
License-File: LICENSE
